.gitignore
LICENSE
README.md
pyproject.toml
requirements.txt
setup.py
.github/workflows/ci.yml
asyncsnmplib/__init__.py
asyncsnmplib/asn1.py
asyncsnmplib/client.py
asyncsnmplib/exceptions.py
asyncsnmplib/package.py
asyncsnmplib/pdu.py
asyncsnmplib/protocol.py
asyncsnmplib/trapserver.py
asyncsnmplib/version.py
asyncsnmplib.egg-info/PKG-INFO
asyncsnmplib.egg-info/SOURCES.txt
asyncsnmplib.egg-info/dependency_links.txt
asyncsnmplib.egg-info/requires.txt
asyncsnmplib.egg-info/top_level.txt
asyncsnmplib/mib/__init__.py
asyncsnmplib/mib/mib.py
asyncsnmplib/mib/mib_index.py
asyncsnmplib/mib/syntax_funs.py
asyncsnmplib/mib/tc.py
asyncsnmplib/mib/utils.py
asyncsnmplib/v3/__init__.py
asyncsnmplib/v3/auth.py
asyncsnmplib/v3/encr.py
asyncsnmplib/v3/package.py
asyncsnmplib/v3/package_dec.py
asyncsnmplib/v3/protocol.py