Metadata-Version: 2.4
Name: asyncsnmplib
Version: 1.0.6
Summary: Library for async SNMP queries
Home-page: https://github.com/cesbit/asyncsnmplib
Download-URL: https://github.com/cesbit/asyncsnmplib/tarball/v1.0.6
Author: Cesbit
Author-email: info@cesbit.com
Keywords: snmp,async
Classifier: Intended Audience :: Developers
Classifier: Operating System :: OS Independent
Classifier: Programming Language :: Python :: 3.9
Classifier: Programming Language :: Python :: 3.10
Classifier: Programming Language :: Python :: 3.11
Classifier: Programming Language :: Python :: 3.12
Classifier: Programming Language :: Python :: 3 :: Only
Classifier: Topic :: Software Development :: Libraries :: Python Modules
License-File: LICENSE
Requires-Dist: pycryptodome
Dynamic: author
Dynamic: author-email
Dynamic: classifier
Dynamic: description
Dynamic: description-content-type
Dynamic: download-url
Dynamic: home-page
Dynamic: keywords
Dynamic: license-file
Dynamic: requires-dist
Dynamic: summary
